optds_core/__init__.py
optds_core/models.py
optds_core/py.typed
optds_core-0.1.0.dist-info/METADATA
optds_core-0.1.0.dist-info/WHEEL
optds_core-0.1.0.dist-info/RECORD
