Metadata-Version: 2.4
Name: optds-core
Version: 0.1.0
Summary: Core types and schemas for OptDS
Author-email: Raeid Saqur <raeid.saqur@maths.ox.ac.uk>
Requires-Python: >=3.10
Requires-Dist: pydantic>=2.0
Requires-Dist: typing-extensions
